marinerg_data_access/__init__.py
marinerg_data_access/admin.py
marinerg_data_access/apps.py
marinerg_data_access/py.typed
marinerg_data_access/urls.py
marinerg_data_access/client/__init__.py
marinerg_data_access/client/client.py
marinerg_data_access/client/zenodo.py
marinerg_data_access/migrations/0001_initial.py
marinerg_data_access/migrations/0002_dataset_id_authority_dataset_keyword_vocabularies_and_more.py
marinerg_data_access/migrations/0003_remove_dataset_keyword_vocabularies_and_more.py
marinerg_data_access/migrations/0004_datasettag_dataset_tags.py
marinerg_data_access/migrations/__init__.py
marinerg_data_access/models/__init__.py
marinerg_data_access/models/dataset.py
marinerg_data_access/models/dataset_template.py
marinerg_data_access/serializers/__init__.py
marinerg_data_access/serializers/dataset.py
marinerg_data_access/serializers/dataset_template.py
marinerg_data_access/utils/__init__.py
marinerg_data_access/utils/test_utils/__init__.py
marinerg_data_access/utils/test_utils/models.py
marinerg_data_access/utils/test_utils/resources.py
marinerg_data_access/view_sets/__init__.py
marinerg_data_access/view_sets/dataset.py
marinerg_data_access/view_sets/dataset_template.py
marinerg_data_access-0.0.10.dist-info/licenses/LICENSE
marinerg_data_access-0.0.10.dist-info/METADATA
marinerg_data_access-0.0.10.dist-info/WHEEL
marinerg_data_access-0.0.10.dist-info/entry_points.txt
marinerg_data_access-0.0.10.dist-info/top_level.txt
marinerg_data_access-0.0.10.dist-info/RECORD
